simple_http_response/__init__.py
simple_http_response/__main__.py
simple_http_response/config.py
simple_http_response-1.1.1.dist-info/licenses/LICENSE
simple_http_response-1.1.1.dist-info/METADATA
simple_http_response-1.1.1.dist-info/WHEEL
simple_http_response-1.1.1.dist-info/entry_points.txt
simple_http_response-1.1.1.dist-info/top_level.txt
simple_http_response-1.1.1.dist-info/RECORD
