Metadata-Version: 2.4
Name: simple-http-response
Version: 1.1.1
Summary: CLI tool to serve a simple HTTP server providing a static response.
Author-email: Louke <git@jannsen.org>
License-Expression: Apache-2.0
Project-URL: Homepage, https://github.com/Louuke/simple-http-response
Project-URL: Repository, https://github.com/Louuke/simple-http-response.git
Classifier: Programming Language :: Python :: 3
Classifier: Operating System :: OS Independent
Classifier: Programming Language :: Python :: Implementation :: CPython
License-File: LICENSE
Requires-Dist: flask>=3.1.0
Requires-Dist: pydantic-settings>=2.8.1
Requires-Dist: waitress>=3.0.2
Provides-Extra: test
Requires-Dist: pytest>=8.3.5; extra == "test"
Dynamic: license-file
